dozent/__init__.py
dozent/__main__.py
dozent/catch_thread_exceptions.py
dozent/downloader_tools.py
dozent/dozent.py
dozent/twitter-archive-stream-links.json
dozent-1.0.1.dist-info/LICENSE
dozent-1.0.1.dist-info/METADATA
dozent-1.0.1.dist-info/WHEEL
dozent-1.0.1.dist-info/top_level.txt
dozent-1.0.1.dist-info/RECORD
