Metadata-Version: 2.1
Name: dozent
Version: 1.0.1
Summary: Dozent is a powerful downloader that is used to download a ton of twitter data from the internet archive.
Home-page: https://github.com/Social-Media-Public-Analysis/dozent
Author: Ali Abbas, Eric Burt, Keelin Becker-Wheeler
Author-email: socialmediapublicanalysis@gmail.com
License: GNU-3
Download-URL: https://github.com/Social-Media-Public-Analysis/dozent/releases/tag/v1.0.1
Keywords: TWITTER,SCRAPER,TWEET
Platform: UNKNOWN
Classifier: Development Status :: 4 - Beta
Classifier: Intended Audience :: Developers
Classifier: Topic :: Software Development :: Build Tools
Classifier: License :: OSI Approved :: MIT License
Classifier: Programming Language :: Python :: 3.9
Requires-Dist: pySmartDL
Requires-Dist: aria2p
Requires-Dist: pytest
Requires-Dist: pyfiglet
Requires-Dist: numpy
Requires-Dist: humanize
